conway_life.cpython-37m-darwin.so
conway_life-0.1.4.1.dist-info/METADATA
conway_life-0.1.4.1.dist-info/WHEEL
conway_life-0.1.4.1.dist-info/top_level.txt
conway_life-0.1.4.1.dist-info/RECORD
