Metadata-Version: 2.1
Name: conway-life
Version: 0.1.4.1
Summary: Python interface for game of life
Home-page: https://github.com/kign/life/tree/master/pni
Author: Konstantin Ignatiev
Author-email: kostya@inet-lab.net
License: UNKNOWN
Project-URL: Bug Tracker, https://github.com/kign/life/issues
Platform: UNKNOWN
Classifier: Programming Language :: C
Classifier: License :: OSI Approved :: GNU General Public License v2 (GPLv2)
Classifier: Operating System :: OS Independent
Requires-Python: >=3
